neopia/__init__.py
neopia/ai_detection.py
neopia/ai_util.py
neopia/connector.py
neopia/keyboard.py
neopia/linker.py
neopia/mode.py
neopia/model.py
neopia/neosoco.py
neopia/neosoco_neobot.py
neopia/opencv_camera.py
neopia/runner.py
neopia/scanner.py
neopia/serial_connector.py
neopia/util.py
neopia/model/efficientdet.tflite
neopia/model/face_detector.tflite
neopia/model/gesture_recognizer.task
neopia/model/ssd_mobilenet_v2.tflite
neopia-0.4.0.dist-info/licenses/LICENSE
neopia-0.4.0.dist-info/METADATA
neopia-0.4.0.dist-info/WHEEL
neopia-0.4.0.dist-info/top_level.txt
neopia-0.4.0.dist-info/RECORD
